CHANGELOG.md
LICENSE
README.md
django_languageselect/__init__.py
django_languageselect/forms.py
django_languageselect/urls.py
django_languageselect/views.py
django_languageselect/templates/languageselect/layer.html
django_languageselect/templatetags/__init__.py
django_languageselect/templatetags/languageselect.py
django_languageselect/tests/__init__.py
django_languageselect/tests/test_django_languageselect.py
django_languageselect-7.0.0.dist-info/METADATA
django_languageselect-7.0.0.dist-info/WHEEL
django_languageselect-7.0.0.dist-info/licenses/LICENSE
django_languageselect-7.0.0.dist-info/RECORD
